wisepy/__init__.py
wisepy/_cmd_parser.py
wisepy/cmd_ast.py
wisepy/cmd_parser.py
wisepy/color.py
wisepy/dynamic_cast.py
wisepy/fn_describe.py
wisepy/talking.py
wisepy-0.2.10.dist-info/METADATA
wisepy-0.2.10.dist-info/RECORD
wisepy-0.2.10.dist-info/WHEEL
wisepy-0.2.10.dist-info/top_level.txt
