Metadata-Version: 2.1
Name: wisepy
Version: 0.2.10
Summary: effective and intuitive CLI framework
Home-page: https://github.com/thautwarm/wisepy
Author: thautwarm
Author-email: twshere@outlook.com
License: MIT
Keywords: CLI solution
Platform: any
Classifier: Programming Language :: Python :: 3.6
Classifier: Programming Language :: Python :: 3.7
Classifier: Programming Language :: Python :: Implementation :: CPython
Requires-Python: >=3.6.0
Requires-Dist: Redy
Requires-Dist: rbnf
Requires-Dist: linq-t
